Flask_Context-0.1.dist-info/DESCRIPTION.rst
Flask_Context-0.1.dist-info/METADATA
Flask_Context-0.1.dist-info/RECORD
Flask_Context-0.1.dist-info/WHEEL
Flask_Context-0.1.dist-info/metadata.json
Flask_Context-0.1.dist-info/top_level.txt
flask_context/__about__.py
flask_context/__init__.py
flask_context/context.py
flask_context/tests/__init__.py
flask_context/tests/test_context.py
