Metadata-Version: 2.0
Name: Flask-Context
Version: 0.1
Summary: Provide an arbitrary context object to Flask. Useful for microservice environments.
Home-page: https://github.com/RealKinetic/Flask-Context
Author: Nick Joyce
Author-email: nick.joyce@realkinetic.com
License: UNKNOWN
Platform: UNKNOWN
Requires-Dist: flask
Requires-Dist: werkzeug
